LICENSE
MANIFEST.in
README.rst
setup.py
bulk_admin/__init__.py
bulk_admin/admin.py
bulk_admin/models.py
bulk_admin/static/bulk_admin/js/bulk-related.js
bulk_admin/static/bulk_admin/js/bulk.js
bulk_admin/templates/bulk_admin/bulk_change_form.html
bulk_admin/templates/bulk_admin/bulk_change_list.html
bulk_admin/templates/bulk_admin/bulk_popup_response.html
django_bulk_admin.egg-info/PKG-INFO
django_bulk_admin.egg-info/SOURCES.txt
django_bulk_admin.egg-info/dependency_links.txt
django_bulk_admin.egg-info/requires.txt
django_bulk_admin.egg-info/top_level.txt