Metadata-Version: 1.1
Name: django-bulk-admin
Version: 0.1.1
Summary: Django bulk admin enables you to bulk add, bulk edit, bulk upload and bulk select in django admin.
Home-page: https://github.com/purelabs/django-bulk-admin
Author: Ruben Grill
Author-email: ruben.grill@gmail.com
License: BSD
Platform: UNKNOWN
Classifier: Environment :: Web Environment
Classifier: Framework :: Django
Classifier: Intended Audience :: Developers
Classifier: License :: OSI Approved :: BSD License
Classifier: Operating System :: OS Independent
Classifier: Programming Language :: Python
Classifier: Programming Language :: Python :: 2
Classifier: Programming Language :: Python :: 2.7
Classifier: Programming Language :: Python :: 3
Classifier: Programming Language :: Python :: 3.2
Classifier: Programming Language :: Python :: 3.3
Classifier: Programming Language :: Python :: 3.4
Classifier: Topic :: Software Development :: Libraries :: Python Modules
